xerparser/__init__.py
xerparser/schemas/__init__.py
xerparser/schemas/_node.py
xerparser/schemas/account.py
xerparser/schemas/actvcode.py
xerparser/schemas/actvtype.py
xerparser/schemas/calendars.py
xerparser/schemas/ermhdr.py
xerparser/schemas/findates.py
xerparser/schemas/memotype.py
xerparser/schemas/pcattype.py
xerparser/schemas/pcatval.py
xerparser/schemas/project.py
xerparser/schemas/projwbs.py
xerparser/schemas/rate.py
xerparser/schemas/rsrc.py
xerparser/schemas/rsrcrate.py
xerparser/schemas/schedoptions.py
xerparser/schemas/task.py
xerparser/schemas/taskfin.py
xerparser/schemas/taskmemo.py
xerparser/schemas/taskpred.py
xerparser/schemas/taskrsrc.py
xerparser/schemas/trsrcfin.py
xerparser/schemas/udftype.py
xerparser/scripts/__init__.py
xerparser/scripts/dates.py
xerparser/scripts/decorators.py
xerparser/src/__init__.py
xerparser/src/errors.py
xerparser/src/parser.py
xerparser/src/utils.py
xerparser/src/validators.py
xerparser/src/xer.py
xerparser-0.13.8.dist-info/LICENSE
xerparser-0.13.8.dist-info/METADATA
xerparser-0.13.8.dist-info/WHEEL
xerparser-0.13.8.dist-info/entry_points.txt
xerparser-0.13.8.dist-info/RECORD
