Metadata-Version: 2.1
Name: xerparser
Version: 0.13.8
Summary: Parse a P6 .xer file to a Python object.
Home-page: https://github.com/jjCode01/xerparser
License: GPL-3.0-only
Keywords: primavera,p6,xer,schedule,scheduling,planning,project management,project controls
Author: Jesse
Author-email: code@seqmanagement.com
Requires-Python: >=3.11,<4.0
Classifier: License :: OSI Approved :: GNU General Public License v3 (GPLv3)
Classifier: Programming Language :: Python :: 3
Classifier: Programming Language :: Python :: 3.11
Classifier: Programming Language :: Python :: 3.12
Classifier: Programming Language :: Python :: 3.13
Requires-Dist: html-sanitizer (>=2.2.0,<3.0.0)
Project-URL: Repository, https://github.com/jjCode01/xerparser
